codechain/__init__.py
codechain/evaluation.py
codechain/generation.py
codechain-0.0.5.dist-info/METADATA
codechain-0.0.5.dist-info/WHEEL
codechain-0.0.5.dist-info/top_level.txt
codechain-0.0.5.dist-info/RECORD
