Metadata-Version: 2.1
Name: codechain
Version: 0.0.5
Summary: Code generation with LLMs
Author: James Murdza
Author-email: <james@jamesmurdza.com>
Project-URL: Source, https://github.com/jamesmurdza/codechain
Keywords: python,llms,codegen,code generation
Classifier: Development Status :: 2 - Pre-Alpha
Classifier: Intended Audience :: Developers
Classifier: Programming Language :: Python :: 3
Classifier: Operating System :: Unix
Classifier: Operating System :: MacOS :: MacOS X
Classifier: Operating System :: Microsoft :: Windows
Requires-Dist: langchain
